LICENSE
MANIFEST.in
README.rst
setup.py
demo/sentry.conf.py
sentry_comments/__init__.py
sentry_comments/forms.py
sentry_comments/models.py
sentry_comments/plugin.py
sentry_comments.egg-info/PKG-INFO
sentry_comments.egg-info/SOURCES.txt
sentry_comments.egg-info/dependency_links.txt
sentry_comments.egg-info/entry_points.txt
sentry_comments.egg-info/not-zip-safe
sentry_comments.egg-info/requires.txt
sentry_comments.egg-info/top_level.txt
sentry_comments/locale/de/LC_MESSAGES/django.mo
sentry_comments/locale/de/LC_MESSAGES/django.po
sentry_comments/migrations/0001_initial.py
sentry_comments/migrations/__init__.py
sentry_comments/templates/sentry_comments/index.html
sentry_comments/templates/sentry_comments/emails/comment.txt